graphene_graphiql_explorer/__init__.py
graphene_graphiql_explorer/static/graphene_graphiql_explorer/css/11.66866c8b.chunk.css
graphene_graphiql_explorer/static/graphene_graphiql_explorer/css/11.66866c8b.chunk.css.map
graphene_graphiql_explorer/static/graphene_graphiql_explorer/css/2.6872d12c.chunk.css
graphene_graphiql_explorer/static/graphene_graphiql_explorer/css/2.6872d12c.chunk.css.map
graphene_graphiql_explorer/static/graphene_graphiql_explorer/css/main.d0b1e8f9.chunk.css
graphene_graphiql_explorer/static/graphene_graphiql_explorer/css/main.d0b1e8f9.chunk.css.map
graphene_graphiql_explorer/static/graphene_graphiql_explorer/js/0.cc0f3dc5.chunk.js
graphene_graphiql_explorer/static/graphene_graphiql_explorer/js/0.cc0f3dc5.chunk.js.map
graphene_graphiql_explorer/static/graphene_graphiql_explorer/js/1.d9165335.chunk.js
graphene_graphiql_explorer/static/graphene_graphiql_explorer/js/1.d9165335.chunk.js.map
graphene_graphiql_explorer/static/graphene_graphiql_explorer/js/11.a1a233cb.chunk.js
graphene_graphiql_explorer/static/graphene_graphiql_explorer/js/11.a1a233cb.chunk.js.map
graphene_graphiql_explorer/static/graphene_graphiql_explorer/js/12.1c33e8cd.chunk.js
graphene_graphiql_explorer/static/graphene_graphiql_explorer/js/12.1c33e8cd.chunk.js.map
graphene_graphiql_explorer/static/graphene_graphiql_explorer/js/13.13fd0b7f.chunk.js
graphene_graphiql_explorer/static/graphene_graphiql_explorer/js/13.13fd0b7f.chunk.js.map
graphene_graphiql_explorer/static/graphene_graphiql_explorer/js/14.eb8c3653.chunk.js
graphene_graphiql_explorer/static/graphene_graphiql_explorer/js/14.eb8c3653.chunk.js.map
graphene_graphiql_explorer/static/graphene_graphiql_explorer/js/15.cbfc0d8e.chunk.js
graphene_graphiql_explorer/static/graphene_graphiql_explorer/js/15.cbfc0d8e.chunk.js.map
graphene_graphiql_explorer/static/graphene_graphiql_explorer/js/16.5a467038.chunk.js
graphene_graphiql_explorer/static/graphene_graphiql_explorer/js/16.5a467038.chunk.js.map
graphene_graphiql_explorer-0.1.1.dist-info/LICENSE
graphene_graphiql_explorer-0.1.1.dist-info/METADATA
graphene_graphiql_explorer-0.1.1.dist-info/WHEEL
graphene_graphiql_explorer-0.1.1.dist-info/top_level.txt
graphene_graphiql_explorer-0.1.1.dist-info/RECORD
