Metadata-Version: 2.1
Name: graphene-graphiql-explorer
Version: 0.1.1
Summary: A Django app that adds graphiql explorer to the graphiql view
Home-page: https://github.com/creimers/graphene-graphiql-explorer
Author: creimers
Author-email: christoph@superservice-international.com
License: MIT
Classifier: Environment :: Web Environment
Classifier: Framework :: Django
Classifier: Intended Audience :: Developers
Classifier: License :: OSI Approved :: MIT License
Classifier: Operating System :: OS Independent
Classifier: Programming Language :: Python
Classifier: Programming Language :: Python :: 3 :: Only
Classifier: Programming Language :: Python :: 3.6
Classifier: Programming Language :: Python :: 3.7
Classifier: Programming Language :: Python :: 3.8
Classifier: Topic :: Internet :: WWW/HTTP
Classifier: Topic :: Internet :: WWW/HTTP :: Dynamic Content
License-File: LICENSE
